pyhwlib/.env.example
pyhwlib/__init__.py
pyhwlib/auto_load_cfg.py
pyhwlib/py.typed
pyhwlib/tests/test.py
pyhwlib-0.2.1.dist-info/WHEEL
pyhwlib-0.2.1.dist-info/entry_points.txt
pyhwlib-0.2.1.dist-info/METADATA
pyhwlib-0.2.1.dist-info/RECORD
